actiapi/__init__.py
actiapi/v2.py
actiapi/v3.py
actiapi-0.3.5.dist-info/METADATA
actiapi-0.3.5.dist-info/WHEEL
actiapi-0.3.5.dist-info/licenses/LICENSE.md
actiapi-0.3.5.dist-info/RECORD
