Metadata-Version: 2.4
Name: actiapi
Version: 0.3.5
Summary: A python package for accessing ActiGraph data through the official ActiGraph API
Project-URL: Repository, https://github.com/actigraph/actiapi
Author-email: ActiGraph Data Science Team <science@theactigraph.com>
Maintainer-email: ActiGraph Data Science Team <science@theactigraph.com>
License-Expression: GPL-3.0-only
License-File: LICENSE.md
Requires-Python: <3.13,>=3.8.1
